manchat.py
manchat-5.dist-info/METADATA
manchat-5.dist-info/WHEEL
manchat-5.dist-info/top_level.txt
manchat-5.dist-info/RECORD
